Orange3_Geo-0.5-py3.11-nspkg.pth
orangecontrib/geo/__init__.py
orangecontrib/geo/cc_cities.py
orangecontrib/geo/mapper.py
orangecontrib/geo/utils.py
orangecontrib/geo/datasets/HDI-small.csv
orangecontrib/geo/datasets/India_census_district_population.csv
orangecontrib/geo/geojson/admin0.json
orangecontrib/geo/geojson/admin1-ABW.json
orangecontrib/geo/geojson/admin1-AFG.json
orangecontrib/geo/geojson/admin1-AGO.json
orangecontrib/geo/geojson/admin1-AIA.json
orangecontrib/geo/geojson/admin1-ALB.json
orangecontrib/geo/geojson/admin1-ALD.json
orangecontrib/geo/geojson/admin1-AND.json
orangecontrib/geo/geojson/admin1-ARE.json
orangecontrib/geo/geojson/admin1-ARG.json
orangecontrib/geo/geojson/admin1-ARM.json
orangecontrib/geo/geojson/admin1-ASM.json
orangecontrib/geo/geojson/admin1-ATA.json
orangecontrib/geo/geojson/admin1-ATC.json
orangecontrib/geo/geojson/admin1-ATF.json
orangecontrib/geo/geojson/admin1-ATG.json
orangecontrib/geo/geojson/admin1-AUS.json
orangecontrib/geo/geojson/admin1-AUT.json
orangecontrib/geo/geojson/admin1-AZE.json
orangecontrib/geo/geojson/admin1-BDI.json
orangecontrib/geo/geojson/admin1-BEL.json
orangecontrib/geo/geojson/admin1-BEN.json
orangecontrib/geo/geojson/admin1-BFA.json
orangecontrib/geo/geojson/admin1-BGD.json
orangecontrib/geo/geojson/admin1-BGR.json
orangecontrib/geo/geojson/admin1-BHR.json
orangecontrib/geo/geojson/admin1-BHS.json
orangecontrib/geo/geojson/admin1-BIH.json
orangecontrib/geo/geojson/admin1-BLM.json
orangecontrib/geo/geojson/admin1-BLR.json
orangecontrib/geo/geojson/admin1-BLZ.json
orangecontrib/geo/geojson/admin1-BMU.json
orangecontrib/geo/geojson/admin1-BOL.json
orangecontrib/geo/geojson/admin1-BRA.json
orangecontrib/geo/geojson/admin1-BRB.json
orangecontrib/geo/geojson/admin1-BRN.json
orangecontrib/geo/geojson/admin1-BTN.json
orangecontrib/geo/geojson/admin1-BWA.json
orangecontrib/geo/geojson/admin1-CAF.json
orangecontrib/geo/geojson/admin1-CAN.json
orangecontrib/geo/geojson/admin1-CHE.json
Orange3_Geo-0.5.dist-info/LICENSE.txt
Orange3_Geo-0.5.dist-info/METADATA
Orange3_Geo-0.5.dist-info/WHEEL
Orange3_Geo-0.5.dist-info/entry_points.txt
Orange3_Geo-0.5.dist-info/namespace_packages.txt
Orange3_Geo-0.5.dist-info/top_level.txt
Orange3_Geo-0.5.dist-info/RECORD
