Metadata-Version: 2.1
Name: Orange3-Geo
Version: 0.5
Summary: Orange add-on for dealing with geography and geo-location.
Home-page: https://github.com/biolab/orange3-geo
Author: Biolab, UL FRI
Author-email: info@biolab.si
License: GPL-3.0
Keywords: orange3 add-on,geographic,visualization,choropleth,map,cartography,location,position,geolocation,geoposition,latitude,longitude
Classifier: Development Status :: 4 - Beta
Classifier: Environment :: X11 Applications :: Qt
Classifier: Environment :: Plugins
Classifier: Programming Language :: Python
Classifier: License :: OSI Approved :: GNU General Public License v3 or later (GPLv3+)
Classifier: Operating System :: OS Independent
Classifier: Topic :: Scientific/Engineering :: Visualization
Classifier: Topic :: Software Development :: Libraries :: Python Modules
Classifier: Intended Audience :: Education
Classifier: Intended Audience :: Science/Research
Classifier: Intended Audience :: Developers
License-File: LICENSE.txt
Requires-Dist: Orange3>=3.37.0
Requires-Dist: scikit-learn
Requires-Dist: pandas
Requires-Dist: scipy>=0.17
Requires-Dist: shapely
Requires-Dist: pyproj
Requires-Dist: simplejson
Requires-Dist: Pillow
Provides-Extra: test
Requires-Dist: coverage; extra == "test"
Provides-Extra: doc
Requires-Dist: sphinx; extra == "doc"
Requires-Dist: recommonmark; extra == "doc"
Requires-Dist: sphinx_rtd_theme; extra == "doc"
